WordTransformer/InputExample.py
WordTransformer/WordTransformer.py
WordTransformer/__init__.py
wordtransformer-0.0.5.dist-info/METADATA
wordtransformer-0.0.5.dist-info/WHEEL
wordtransformer-0.0.5.dist-info/RECORD
