Metadata-Version: 2.3
Name: WordTransformer
Version: 0.0.5
Summary: WiC Pretrained Model for Cross-Lingual LEXical sEMantic changE
Project-URL: Homepage, https://github.com/pierluigic/xl-lexeme
Author-email: Pierluigi Cassotti <p@x.com>
Classifier: License :: OSI Approved :: MIT License
Classifier: Operating System :: OS Independent
Classifier: Programming Language :: Python :: 3
Requires-Python: >=3.8
Requires-Dist: huggingface-hub<0.26.0
Requires-Dist: sentence-transformers<3.0.0
